Metadata-Version: 1.1
Name: pymiproxy
Version: 1.0
Summary: Micro Interceptor Proxy - a simple MITM HTTP/S proxy
Home-page: https://github.com/allfro/pymiproxy
Author: Nadeem Douba
Author-email: ndouba@gmail.com
License: GPL
Download-URL: https://github.com/allfro/pymiproxy/zipball/master
Platform: UNKNOWN
